discord_mod_bot/__init__.py
discord_mod_bot/bot.py
discord_mod_bot/commands.py
discord_mod_bot/config.py
discord_mod_bot/database.py
discord_mod_bot/slash_commands.py
discord_mod_bot/utils.py
discordmodbot-1.0.0.dist-info/licenses/LICENSE
discordmodbot-1.0.0.dist-info/METADATA
discordmodbot-1.0.0.dist-info/WHEEL
discordmodbot-1.0.0.dist-info/top_level.txt
discordmodbot-1.0.0.dist-info/RECORD
