Metadata-Version: 2.4
Name: discordmodbot
Version: 1.0.0
Summary: A comprehensive Discord moderation bot library with minimal setup required
Author-email: TechEd Lab Team <vyeronservices.official@gmail.com>
License: MIT
Project-URL: Homepage, https://github.com/discordmodbot/discordmodbot
Project-URL: Repository, https://github.com/discordmodbot/discordmodbot
Project-URL: Documentation, https://github.com/discordmodbot/discordmodbot/wiki
Project-URL: Bug Reports, https://github.com/discordmodbot/discordmodbot/issues
Project-URL: Discord Support, https://discord.gg/pqWMR5gS
Keywords: discord,bot,moderation,admin,management,slash-commands,prefix-commands
Classifier: Development Status :: 5 - Production/Stable
Classifier: Intended Audience :: Developers
Classifier: Operating System :: OS Independent
Classifier: Programming Language :: Python :: 3
Classifier: Programming Language :: Python :: 3.8
Classifier: Programming Language :: Python :: 3.9
Classifier: Programming Language :: Python :: 3.10
Classifier: Programming Language :: Python :: 3.11
Classifier: Programming Language :: Python :: 3.12
Classifier: Topic :: Communications :: Chat
Classifier: Topic :: Internet
Classifier: Topic :: Software Development :: Libraries :: Python Modules
Requires-Python: >=3.8
License-File: LICENSE
Requires-Dist: discord.py>=2.3.0
Dynamic: license-file
